lyne/__init__.py
lyne/_core.py
lyne/_dims.py
lyne/_proxy.py
lyne/_stream_item.py
lyne/_stream_op.py
lyne/clip.py
lyne/cv.py
lyne/fs.py
lyne/util.py
lyne-0.0.1.dist-info/LICENSE.txt
lyne-0.0.1.dist-info/METADATA
lyne-0.0.1.dist-info/WHEEL
lyne-0.0.1.dist-info/top_level.txt
lyne-0.0.1.dist-info/RECORD
