Metadata-Version: 2.1
Name: lyne
Version: 0.0.1
Summary: A Python processing pipeline
Author: Shondoit Walker
License: GNU AFFERO GENERAL PUBLIC LICENSE
Project-URL: homepage, https://github.com/Shondoit/lyne
Project-URL: repository, https://github.com/Shondoit/lyne
Classifier: Programming Language :: Python :: 3
Classifier: Operating System :: OS Independent
License-File: LICENSE.txt
Provides-Extra: clip
Requires-Dist: transformers (>=4.26.0) ; extra == 'clip'
Provides-Extra: image
Requires-Dist: matplotlib (>=3.6.2) ; extra == 'image'
Requires-Dist: numpy (>=1.24.0) ; extra == 'image'
Requires-Dist: opencv-python (>=4.7.0.68) ; extra == 'image'
Requires-Dist: Pillow (>=9.3.0) ; extra == 'image'
Provides-Extra: interactive
Requires-Dist: jupyterlab (>=3.5.2) ; extra == 'interactive'
